CHANGELOG
LICENSE
README
ez_setup.py
setup.py
django_svnlit.egg-info/PKG-INFO
django_svnlit.egg-info/SOURCES.txt
django_svnlit.egg-info/dependency_links.txt
django_svnlit.egg-info/top_level.txt
svnlit/__init__.py
svnlit/admin.py
svnlit/choices.py
svnlit/decorators.py
svnlit/diff.py
svnlit/exceptions.py
svnlit/forms.py
svnlit/managers.py
svnlit/models.py
svnlit/urls.py
svnlit/views.py
svnlit/management/__init__.py
svnlit/management/commands/__init__.py
svnlit/management/commands/svnadd.py
svnlit/management/commands/svnclean.py
svnlit/management/commands/svnsync.py
svnlit/templates/base.html
svnlit/templates/svnlit/base.html
svnlit/templates/svnlit/changeset.html
svnlit/templates/svnlit/changeset_list.html
svnlit/templates/svnlit/changeset_list_pagination.html
svnlit/templates/svnlit/node_base.html
svnlit/templates/svnlit/node_diff.html
svnlit/templates/svnlit/node_diff_data.html
svnlit/templates/svnlit/node_directory.html
svnlit/templates/svnlit/node_file.html
svnlit/templates/svnlit/node_invalid.html
svnlit/templates/svnlit/node_path.html
svnlit/templates/svnlit/repository_diff.html
svnlit/templates/svnlit/repository_list.html
svnlit/templatetags/__init__.py
svnlit/templatetags/timesince.py