Metadata-Version: 1.0
Name: django-svnlit
Version: 0.1.1
Summary: Django-based subversion browser.
Home-page: http://code.google.com/p/django-svnlit/
Author: Tamas Kemenczy
Author-email: tamas.kemenczy@gmail.com
License: BSD
Keywords: django subversion svn browser
Platform: UNKNOWN
Classifier: Development Status :: 2 - Pre-Alpha
Classifier: Environment :: Web Environment
Classifier: Framework :: Django
Classifier: Intended Audience :: Developers
Classifier: License :: OSI Approved :: BSD License
Classifier: Operating System :: OS Independent
Classifier: Programming Language :: Python
